launchcontainer/__init__.py
launchcontainer/browser_tests.py
launchcontainer/launchcontainer.py
launchcontainer/test_settings.py
launchcontainer/tests.py
launchcontainer/static/css/launchcontainer.css
launchcontainer/static/css/launchcontainer_edit.css
launchcontainer/static/html/launchcontainer.html
launchcontainer/static/html/launchcontainer_edit.html
launchcontainer/static/js/src/launchcontainer.js
launchcontainer/static/js/src/launchcontainer_edit.js
xblock_launchcontainer-4.0.0.dist-info/LICENSE
xblock_launchcontainer-4.0.0.dist-info/METADATA
xblock_launchcontainer-4.0.0.dist-info/WHEEL
xblock_launchcontainer-4.0.0.dist-info/entry_points.txt
xblock_launchcontainer-4.0.0.dist-info/top_level.txt
xblock_launchcontainer-4.0.0.dist-info/RECORD
