Metadata-Version: 2.1
Name: xblock-launchcontainer
Version: 4.0.0
Summary: Open EdX XBlock to display a button allowing an LMS user to launch and link to an external courseware resource via the Wharf container API
Home-page: UNKNOWN
Author: Bryan Wilson, Appsembler
Author-email: UNKNOWN
License: UNKNOWN
Platform: UNKNOWN
Requires-Dist: XBlock
Requires-Dist: django-crum
Requires-Dist: xblock-utils
